CHANGES
LICENSE
MANIFEST.in
README.md
setup.py
django_ipapi.egg-info/PKG-INFO
django_ipapi.egg-info/SOURCES.txt
django_ipapi.egg-info/dependency_links.txt
django_ipapi.egg-info/not-zip-safe
django_ipapi.egg-info/requires.txt
django_ipapi.egg-info/top_level.txt
ipapi/__init__.py
ipapi/client.py
ipapi/middleware.py
ipapi/models.py
ipapi/test_runner.py
ipapi/tests.py
ipapi/urls.py
ipapi/version.py
ipapi/views.py