Metadata-Version: 1.1
Name: django-ipapi
Version: 0.0.1b1
Summary: Django IP-API.com wrapper
Home-page: https://bitbucket.org/sizeof/django-ipapi
Author: Mariusz Smenżyk
Author-email: mariusz.smenzyk@sizeof.pl
License: BSD
Keywords: django ip blocking api ip-api.com
Platform: UNKNOWN
Classifier: Environment :: Web Environment
Classifier: Framework :: Django
Classifier: License :: OSI Approved :: BSD License
Classifier: Operating System :: OS Independent
Classifier: Programming Language :: Python
